regexf/__init__.py
regexf/regexf_version.py
regexf-0.2.post1.data/scripts/assertequal.sh
regexf-0.2.post1.data/scripts/assertfalse.sh
regexf-0.2.post1.data/scripts/assertgrep.sh
regexf-0.2.post1.data/scripts/asserttrue.sh
regexf-0.2.post1.data/scripts/regexf
regexf-0.2.post1.data/scripts/regexf.ini
regexf-0.2.post1.data/scripts/regexf_test.ini
regexf-0.2.post1.data/scripts/regexf_test.sh
regexf-0.2.post1.data/scripts/regexf_version.py
regexf-0.2.post1.dist-info/DESCRIPTION.rst
regexf-0.2.post1.dist-info/METADATA
regexf-0.2.post1.dist-info/RECORD
regexf-0.2.post1.dist-info/WHEEL
regexf-0.2.post1.dist-info/metadata.json
regexf-0.2.post1.dist-info/top_level.txt
