Metadata-Version: 2.0
Name: regexf
Version: 0.2.post1
Summary: Compare regular expressions against those in a file
Home-page: http://pypi.python.org/pypi/regexf/
Author: Martin Mohan
Author-email: martinmohan@yahoo.com
License: LICENSE.txt
Platform: UNKNOWN
Classifier: Development Status :: 3 - Alpha
Classifier: Environment :: Console
Classifier: Environment :: Web Environment
Classifier: Intended Audience :: Developers
Classifier: Intended Audience :: System Administrators
Classifier: License :: OSI Approved :: GNU General Public License (GPL)
Classifier: Programming Language :: Python
Classifier: Topic :: System
Classifier: Topic :: Software Development
